README.txt
setup.py
dataschema/__init__.py
dataschema/dataschema.py
dataschema.egg-info/PKG-INFO
dataschema.egg-info/SOURCES.txt
dataschema.egg-info/dependency_links.txt
dataschema.egg-info/top_level.txt
dataschema/tests/__init__.py
dataschema/tests/test_dataschema.py