Metadata-Version: 1.1
Name: dataschema
Version: 0.1
Summary: Schema validation for Python data structures
Home-page: https://pypi.python.org/pypi/dataschema/
Author: Stefan W
Author-email: stefan+pypi@geeky.net
License: MIT
Keywords: data schema validation
Platform: UNKNOWN
Classifier: Intended Audience :: Developers
Classifier: License :: OSI Approved :: MIT License
Classifier: Programming Language :: Python :: 2
Classifier: Programming Language :: Python :: 2.7
